{
  "es": {
    "SettingsAddCardButton": "Agregar tarjeta",
    "SettingsCardExpMonthLabel": "Mes de vencimiento",
    "SettingsCardExpYearLabel": "Ano de vencimiento",
    "SettingsDisbursementMethod": "No configurado.",
    "SettingsDisplayNamePlaceholder": "Su nombre visible",
    "SettingsGatewayBankLabel": "Transferencia bancaria",
    "SettingsGatewayCardLabel": "Tarjeta de credito / debito",
    "SettingsGatewayQrPhLabel": "QR Ph (escanear para pagar)",
    "SettingsGatewaysDescription": "Active o desactive los metodos de pago para su cuenta.",
    "SettingsGatewaysHeading": "Pasarelas de pago",
    "SettingsKycDigitVerifyButton": "Verificar con Didit",
    "SettingsKycDocumentTypeDrivers": "Licencia de conducir",
    "SettingsKycDocumentTypeSelect": "Seleccione el tipo de documento",
    "SettingsLinkedWallet": "No hay billetera vinculada.",
    "SettingsNoInvoices": "No hay historial de facturas disponible.",
    "SettingsNoSavedCards": "No hay tarjetas guardadas. Agregue una tarjeta abajo."
  },
  "fil": {
    "SettingsAddCardButton": "Magdagdag ng card",
    "SettingsCardExpMonthLabel": "Buwan ng pag-expire",
    "SettingsCardExpYearLabel": "Taon ng pag-expire",
    "SettingsDisbursementMethod": "Hindi naka-configure.",
    "SettingsDisplayNamePlaceholder": "Iyong display name",
    "SettingsGatewayBankLabel": "Paglipat sa bangko",
    "SettingsGatewayCardLabel": "Credit / Debit card",
    "SettingsGatewayQrPhLabel": "QR Ph (i-scan para magbayad)",
    "SettingsGatewaysDescription": "I-enable o i-disable ang mga paraan ng pagbabayad para sa iyong account.",
    "SettingsGatewaysHeading": "Mga payment gateway",
    "SettingsKycDigitVerifyButton": "Beripikahin sa Didit",
    "SettingsKycDocumentTypeDrivers": "Lisensya sa pagmamaneho",
    "SettingsKycDocumentTypeSelect": "Piliin ang uri ng dokumento",
    "SettingsLinkedWallet": "Walang nakakabit na wallet.",
    "SettingsNoInvoices": "Walang available na kasaysayan ng invoice.",
    "SettingsNoSavedCards": "Walang naka-save na card. Magdagdag ng card sa ibaba."
  },
  "fr": {
    "SettingsAddCardButton": "Ajouter une carte",
    "SettingsCardExpMonthLabel": "Mois d'expiration",
    "SettingsCardExpYearLabel": "Annee d'expiration",
    "SettingsDisbursementMethod": "Non configure.",
    "SettingsDisplayNamePlaceholder": "Votre nom d'affichage",
    "SettingsGatewayBankLabel": "Virement bancaire",
    "SettingsGatewayCardLabel": "Carte de credit / debit",
    "SettingsGatewayQrPhLabel": "QR Ph (scanner pour payer)",
    "SettingsGatewaysDescription": "Activez ou desactivez les moyens de paiement pour votre compte.",
    "SettingsGatewaysHeading": "Passerelles de paiement",
    "SettingsKycDigitVerifyButton": "Verifier avec Didit",
    "SettingsKycDocumentTypeDrivers": "Permis de conduire",
    "SettingsKycDocumentTypeSelect": "Selectionnez le type de document",
    "SettingsLinkedWallet": "Aucun portefeuille lie.",
    "SettingsNoInvoices": "Aucun historique de factures disponible.",
    "SettingsNoSavedCards": "Aucune carte enregistree. Ajoutez une carte ci-dessous."
  },
  "hi": {
    "SettingsAddCardButton": "कार्ड जोड़ें",
    "SettingsCardExpMonthLabel": "समाप्ति माह",
    "SettingsCardExpYearLabel": "समाप्ति वर्ष",
    "SettingsDisbursementMethod": "कॉन्फ़िगर नहीं किया गया।",
    "SettingsDisplayNamePlaceholder": "आपका प्रदर्शित नाम",
    "SettingsGatewayBankLabel": "बैंक ट्रांसफर",
    "SettingsGatewayCardLabel": "क्रेडिट / डेबिट कार्ड",
    "SettingsGatewayQrPhLabel": "QR Ph (स्कैन करके भुगतान करें)",
    "SettingsGatewaysDescription": "अपने खाते के लिए भुगतान विधियों को सक्षम या अक्षम करें।",
    "SettingsGatewaysHeading": "भुगतान गेटवे",
    "SettingsKycDigitVerifyButton": "Didit के साथ सत्यापित करें",
    "SettingsKycDocumentTypeDrivers": "ड्राइविंग लाइसेंस",
    "SettingsKycDocumentTypeSelect": "दस्तावेज़ प्रकार चुनें",
    "SettingsLinkedWallet": "कोई वॉलेट लिंक नहीं है।",
    "SettingsNoInvoices": "कोई इनवॉइस इतिहास उपलब्ध नहीं है।",
    "SettingsNoSavedCards": "कोई सहेजे गए कार्ड नहीं हैं। नीचे एक कार्ड जोड़ें।"
  },
  "id": {
    "SettingsAddCardButton": "Tambahkan kartu",
    "SettingsCardExpMonthLabel": "Bulan kedaluwarsa",
    "SettingsCardExpYearLabel": "Tahun kedaluwarsa",
    "SettingsDisbursementMethod": "Belum dikonfigurasi.",
    "SettingsDisplayNamePlaceholder": "Nama tampilan Anda",
    "SettingsGatewayBankLabel": "Transfer bank",
    "SettingsGatewayCardLabel": "Kartu kredit / debit",
    "SettingsGatewayQrPhLabel": "QR Ph (pindai untuk membayar)",
    "SettingsGatewaysDescription": "Aktifkan atau nonaktifkan metode pembayaran untuk akun Anda.",
    "SettingsGatewaysHeading": "Gerbang pembayaran",
    "SettingsKycDigitVerifyButton": "Verifikasi dengan Didit",
    "SettingsKycDocumentTypeDrivers": "SIM",
    "SettingsKycDocumentTypeSelect": "Pilih jenis dokumen",
    "SettingsLinkedWallet": "Belum ada dompet yang ditautkan.",
    "SettingsNoInvoices": "Tidak ada riwayat faktur yang tersedia.",
    "SettingsNoSavedCards": "Belum ada kartu tersimpan. Tambahkan kartu di bawah."
  },
  "it": {
    "SettingsAddCardButton": "Aggiungi carta",
    "SettingsCardExpMonthLabel": "Mese di scadenza",
    "SettingsCardExpYearLabel": "Anno di scadenza",
    "SettingsDisbursementMethod": "Non configurato.",
    "SettingsDisplayNamePlaceholder": "Il tuo nome visualizzato",
    "SettingsGatewayBankLabel": "Bonifico bancario",
    "SettingsGatewayCardLabel": "Carta di credito / debito",
    "SettingsGatewayQrPhLabel": "QR Ph (scansiona per pagare)",
    "SettingsGatewaysDescription": "Abilita o disabilita i metodi di pagamento per il tuo account.",
    "SettingsGatewaysHeading": "Gateway di pagamento",
    "SettingsKycDigitVerifyButton": "Verifica con Didit",
    "SettingsKycDocumentTypeDrivers": "Patente di guida",
    "SettingsKycDocumentTypeSelect": "Seleziona il tipo di documento",
    "SettingsLinkedWallet": "Nessun portafoglio collegato.",
    "SettingsNoInvoices": "Nessuna cronologia fatture disponibile.",
    "SettingsNoSavedCards": "Nessuna carta salvata. Aggiungi una carta qui sotto."
  },
  "ja": {
    "SettingsAddCardButton": "カードを追加",
    "SettingsCardExpMonthLabel": "有効期限（月）",
    "SettingsCardExpYearLabel": "有効期限（年）",
    "SettingsDisbursementMethod": "未設定です。",
    "SettingsDisplayNamePlaceholder": "表示名",
    "SettingsGatewayBankLabel": "銀行振込",
    "SettingsGatewayCardLabel": "クレジット / デビットカード",
    "SettingsGatewayQrPhLabel": "QR Ph（スキャンして支払う）",
    "SettingsGatewaysDescription": "アカウントの支払い方法を有効または無効にします。",
    "SettingsGatewaysHeading": "決済ゲートウェイ",
    "SettingsKycDigitVerifyButton": "Didit で認証",
    "SettingsKycDocumentTypeDrivers": "運転免許証",
    "SettingsKycDocumentTypeSelect": "書類の種類を選択",
    "SettingsLinkedWallet": "連携されたウォレットはありません。",
    "SettingsNoInvoices": "請求書の履歴はありません。",
    "SettingsNoSavedCards": "保存されたカードはありません。下でカードを追加してください。"
  },
  "ko": {
    "SettingsAddCardButton": "카드 추가",
    "SettingsCardExpMonthLabel": "만료 월",
    "SettingsCardExpYearLabel": "만료 연도",
    "SettingsDisbursementMethod": "설정되지 않음.",
    "SettingsDisplayNamePlaceholder": "표시 이름",
    "SettingsGatewayBankLabel": "은행 송금",
    "SettingsGatewayCardLabel": "신용 / 직불 카드",
    "SettingsGatewayQrPhLabel": "QR Ph (스캔하여 결제)",
    "SettingsGatewaysDescription": "계정의 결제 수단을 활성화하거나 비활성화합니다.",
    "SettingsGatewaysHeading": "결제 게이트웨이",
    "SettingsKycDigitVerifyButton": "Didit으로 인증",
    "SettingsKycDocumentTypeDrivers": "운전면허증",
    "SettingsKycDocumentTypeSelect": "문서 유형 선택",
    "SettingsLinkedWallet": "연결된 지갑이 없습니다.",
    "SettingsNoInvoices": "청구서 기록이 없습니다.",
    "SettingsNoSavedCards": "저장된 카드가 없습니다. 아래에서 카드를 추가하세요."
  },
  "nl": {
    "SettingsAddCardButton": "Kaart toevoegen",
    "SettingsCardExpMonthLabel": "Vervalmaand",
    "SettingsCardExpYearLabel": "Vervaljaar",
    "SettingsDisbursementMethod": "Niet geconfigureerd.",
    "SettingsDisplayNamePlaceholder": "Uw weergavenaam",
    "SettingsGatewayBankLabel": "Bankoverschrijving",
    "SettingsGatewayCardLabel": "Creditcard / betaalkaart",
    "SettingsGatewayQrPhLabel": "QR Ph (scannen om te betalen)",
    "SettingsGatewaysDescription": "Schakel betaalmethoden voor uw account in of uit.",
    "SettingsGatewaysHeading": "Betaalgateways",
    "SettingsKycDigitVerifyButton": "Verifieer met Didit",
    "SettingsKycDocumentTypeDrivers": "Rijbewijs",
    "SettingsKycDocumentTypeSelect": "Selecteer documenttype",
    "SettingsLinkedWallet": "Geen wallet gekoppeld.",
    "SettingsNoInvoices": "Geen factuurgeschiedenis beschikbaar.",
    "SettingsNoSavedCards": "Geen opgeslagen kaarten. Voeg hieronder een kaart toe."
  },
  "pt": {
    "SettingsAddCardButton": "Adicionar cartao",
    "SettingsCardExpMonthLabel": "Mes de validade",
    "SettingsCardExpYearLabel": "Ano de validade",
    "SettingsDisbursementMethod": "Nao configurado.",
    "SettingsDisplayNamePlaceholder": "Seu nome de exibicao",
    "SettingsGatewayBankLabel": "Transferencia bancaria",
    "SettingsGatewayCardLabel": "Cartao de credito / debito",
    "SettingsGatewayQrPhLabel": "QR Ph (escaneie para pagar)",
    "SettingsGatewaysDescription": "Ative ou desative os metodos de pagamento da sua conta.",
    "SettingsGatewaysHeading": "Gateways de pagamento",
    "SettingsKycDigitVerifyButton": "Verificar com Didit",
    "SettingsKycDocumentTypeDrivers": "Carteira de motorista",
    "SettingsKycDocumentTypeSelect": "Selecione o tipo de documento",
    "SettingsLinkedWallet": "Nenhuma carteira vinculada.",
    "SettingsNoInvoices": "Nenhum historico de faturas disponivel.",
    "SettingsNoSavedCards": "Nenhum cartao salvo. Adicione um cartao abaixo."
  },
  "ru": {
    "SettingsAddCardButton": "Добавить карту",
    "SettingsCardExpMonthLabel": "Месяц истечения",
    "SettingsCardExpYearLabel": "Год истечения",
    "SettingsDisbursementMethod": "Не настроено.",
    "SettingsDisplayNamePlaceholder": "Ваше отображаемое имя",
    "SettingsGatewayBankLabel": "Банковский перевод",
    "SettingsGatewayCardLabel": "Кредитная / дебетовая карта",
    "SettingsGatewayQrPhLabel": "QR Ph (сканировать для оплаты)",
    "SettingsGatewaysDescription": "Включите или отключите способы оплаты для своей учетной записи.",
    "SettingsGatewaysHeading": "Платежные шлюзы",
    "SettingsKycDigitVerifyButton": "Подтвердить через Didit",
    "SettingsKycDocumentTypeDrivers": "Водительское удостоверение",
    "SettingsKycDocumentTypeSelect": "Выберите тип документа",
    "SettingsLinkedWallet": "Кошелек не привязан.",
    "SettingsNoInvoices": "История счетов недоступна.",
    "SettingsNoSavedCards": "Сохраненных карт нет. Добавьте карту ниже."
  },
  "tr": {
    "SettingsAddCardButton": "Kart ekle",
    "SettingsCardExpMonthLabel": "Son kullanma ayi",
    "SettingsCardExpYearLabel": "Son kullanma yili",
    "SettingsDisbursementMethod": "Yapilandirilmadi.",
    "SettingsDisplayNamePlaceholder": "Gorunen adiniz",
    "SettingsGatewayBankLabel": "Banka havalesi",
    "SettingsGatewayCardLabel": "Kredi / banka karti",
    "SettingsGatewayQrPhLabel": "QR Ph (odemek icin tara)",
    "SettingsGatewaysDescription": "Hesabiniz icin odeme yontemlerini etkinlestirin veya devre disi birakin.",
    "SettingsGatewaysHeading": "Odeme ag gecitleri",
    "SettingsKycDigitVerifyButton": "Didit ile dogrula",
    "SettingsKycDocumentTypeDrivers": "Surucu belgesi",
    "SettingsKycDocumentTypeSelect": "Belge turunu secin",
    "SettingsLinkedWallet": "Bagli cuzdan yok.",
    "SettingsNoInvoices": "Fatura gecmisi yok.",
    "SettingsNoSavedCards": "Kayitli kart yok. Asagidan bir kart ekleyin."
  }
}
